{"MeteoDate":"18.03.23","MeteoTime":"13:14","WindDir":"Юг","WindSpeed":1.1,"Pressure":750,"TempMin":19.1,"TempMax":30.3,"Precipitation":10.0,"SunshineDuration":12.35,"DewPoint":89.3,"SnowLevelWeatherSite":210,"SnowCoverage":100,"SnowLevelForest":190,"AverageSnowDensity":500.23,"MoistureWaterInSnow":10,"SnowCover":"полностью","SnowState":"талый","NRustayskoyeWaterLevel":15,"NRustayskoyeTemp":20.1,"NRustayskoyepH":5.5,"NRustayskoyeElConduct":237,"NRustayskoyeWaterColor":10,"NRustayskoyeOxygen":80.3,"NRustayskoyeBPK5":12.12,"KrugloeWaterLevel":10,"KrugloeTemp":20.2,"KrugloepH":5.5,"KrugloeElConduct":123,"KrugloeWaterColor":10,"KrugloeOxygen":81.1,"KrugloeBPK5":12.12,"KalachikWaterLevel":220,"KalachikTemp":15.9,"KalachikpH":5.5,"KalachikElConduct":123,"KalachikWaterColor":9,"KalachikOxygen":20.2,"KalachikBPK5":123.321,"MakhovskoeWaterLevel":120,"MakhovskoeTemp":17.1,"MakhovskoepH":5.6,"MakhovskoeElConduct":300,"MakhovskoeWaterColor":10,"MakhovskoeOxygen":70.2,"MakhovskoeBPK5":123.987,"KerzhenetsWaterLevel":253,"KerzhenetsTemp":20.1,"KerzhenetspH":6.6,"KerzhenetsElConduct":125,"KerzhenetsWaterColor":9,"KerzhenetsOxygen":81.2,"KerzhenetsBPK5":123.453,"VishnyaWaterLevel":245,"VishnyaTemp":21.1,"VishnyapH":4.5,"VishnyaElConduct":345,"VishnyaWaterColor":8,"VishnyaOxygen":87.3,"VishnyaBPK5":123.123,"WellWaterLevel":231,"WellTemp":18.1,"WellpH":5.6,"WellElConduct":123,"WellWaterColor":9,"WellOxygen":80.3,"WellBPK5":123.321,"VishenskoeWaterLevel":120,"VishenskoeTemp":20.1,"VishenskoepH":5.5,"VishenskoeElConduct":789,"VishenskoeWaterColor":11,"VishenskoeOxygen":90.1,"VishenskoeBPK5":123.32}